__init__.py
strapi_client/__init__.py
strapi_client/py.typed
strapi_client/strapi_client.py
strapi_client/strapi_client_async.py
strapi_client/strapi_client_base.py
strapi_client/types.py
strapi_client/utils.py
strapi_client/models/__init__.py
strapi_client/models/active_document.py
strapi_client/models/api_parameters.py
strapi_client/models/auth.py
strapi_client/models/base_component.py
strapi_client/models/base_document.py
strapi_client/models/base_populatable.py
strapi_client/models/file_payload.py
strapi_client/models/media_image_document.py
strapi_client/models/response.py
strapi_client/models/single_smart_document.py
strapi_client/models/smart_document.py
strapi_client/models/smart_document_utils.py
strapi_client/models/webhook_payload.py
strapi_client-5.0.4.dist-info/licenses/LICENSE
strapi_client-5.0.4.dist-info/METADATA
strapi_client-5.0.4.dist-info/WHEEL
strapi_client-5.0.4.dist-info/top_level.txt
strapi_client-5.0.4.dist-info/RECORD
