Metadata-Version: 2.4
Name: strapi-client
Version: 5.0.4
Summary: Interact with Strapi from Python using the REST API
Author-email: Pavel Roslovets <p.v.roslovets@gmail.com>
License: MIT
Project-URL: Homepage, https://github.com/Roslovets-Inc/strapi-client
Project-URL: Repository, https://github.com/Roslovets-Inc/strapi-client
Project-URL: Documentation, https://roslovets-inc.github.io/strapi-client/
Project-URL: Issues, https://github.com/Roslovets-Inc/strapi-client/issues
Project-URL: Changelog, https://github.com/Roslovets-Inc/strapi-client/blob/main/CHANGELOG.md
Keywords: strapi,cms,api,rest
Classifier: Programming Language :: Python :: 3
Classifier: License :: OSI Approved :: MIT License
Classifier: Operating System :: OS Independent
Requires-Python: >=3.10
License-File: LICENSE
Requires-Dist: httpx>=0.23.1
Requires-Dist: pydantic>=2.0
Requires-Dist: qs-codec>=1.1.5
Dynamic: license-file
